{
  "product": [
    {
      "id": "species",
      "keys": { "tr": "Tür", "en": "Species" },
      "labels": { "tr": "Tür", "en": "Species" }
    },
    {
      "id": "variety",
      "keys": { "tr": "Çeşit", "en": "Variety" },
      "labels": { "tr": "Çeşit", "en": "Variety" }
    },
    {
      "id": "height",
      "keys": { "tr": "Boy", "en": "Height" },
      "labels": { "tr": "Boy", "en": "Height" }
    },
    {
      "id": "root_type",
      "keys": { "tr": "Kök Tipi", "en": "Root Type" },
      "labels": { "tr": "Kök Tipi", "en": "Root Type" }
    },
    {
      "id": "planting_season",
      "keys": { "tr": "Dikim Zamanı", "en": "Planting Season" },
      "labels": { "tr": "Dikim Zamanı", "en": "Planting Season" }
    },
    {
      "id": "harvest_season",
      "keys": { "tr": "Hasat Zamanı", "en": "Harvest Season" },
      "labels": { "tr": "Hasat Zamanı", "en": "Harvest Season" }
    },
    {
      "id": "soil_type",
      "keys": { "tr": "Toprak Tipi", "en": "Soil Type" },
      "labels": { "tr": "Toprak Tipi", "en": "Soil Type" }
    },
    {
      "id": "sun_exposure",
      "keys": { "tr": "Güneş İhtiyacı", "en": "Sun Exposure" },
      "labels": { "tr": "Güneş İhtiyacı", "en": "Sun Exposure" }
    },
    {
      "id": "watering",
      "keys": { "tr": "Sulama", "en": "Watering" },
      "labels": { "tr": "Sulama", "en": "Watering" }
    },
    {
      "id": "frost_resistance",
      "keys": { "tr": "Soğuğa Dayanıklılık", "en": "Frost Resistance" },
      "labels": { "tr": "Soğuğa Dayanıklılık", "en": "Frost Resistance" }
    },
    {
      "id": "pot_size",
      "keys": { "tr": "Saksı Boyutu", "en": "Pot Size" },
      "labels": { "tr": "Saksı Boyutu", "en": "Pot Size" }
    },
    {
      "id": "yield",
      "keys": { "tr": "Verim", "en": "Yield" },
      "labels": { "tr": "Verim", "en": "Yield" }
    },
    {
      "id": "maturity_days",
      "keys": { "tr": "Olgunlaşma Süresi", "en": "Maturity Days" },
      "labels": { "tr": "Olgunlaşma Süresi", "en": "Maturity Days" }
    },
    {
      "id": "origin",
      "keys": { "tr": "Menşei", "en": "Origin" },
      "labels": { "tr": "Menşei", "en": "Origin" }
    }
  ]
}
